bayes_kit/__init__.py
bayes_kit-0.0.1a0.dist-info/LICENSE-CODE
bayes_kit-0.0.1a0.dist-info/METADATA
bayes_kit-0.0.1a0.dist-info/WHEEL
bayes_kit-0.0.1a0.dist-info/top_level.txt
bayes_kit-0.0.1a0.dist-info/RECORD
