Metadata-Version: 2.1
Name: bayes-kit
Version: 0.0.1a0
Home-page: https://github.com/flatironinstitute/bayes-kit
Requires-Python: >=3.9
License-File: LICENSE-CODE
Requires-Dist: numpy
Provides-Extra: test
Requires-Dist: pytest ; extra == 'test'
Requires-Dist: scipy ; extra == 'test'
